[
  {
    "line": 1,
    "elements": [
      {
        "before": [
          {
            "result": {
              "duration": 3797661991,
              "status": "passed"
            },
            "match": {
              "location": "CucumberTestBeforeAndAfter.setUp()"
            }
          }
        ],
        "line": 3,
        "name": "go through all auction activities and open some other parts of site",
        "description": "",
        "id": "performance-test-1,-collecting-metric-to-excel-file;go-through-all-auction-activities-and-open-some-other-parts-of-site",
        "after": [
          {
            "result": {
              "duration": 3403074473,
              "status": "passed"
            },
            "match": {
              "location": "CucumberTestBeforeAndAfter.tearDown()"
            }
          }
        ],
        "type": "scenario",
        "keyword": "Scenario",
        "steps": [
          {
            "result": {
              "duration": 102374029,
              "status": "passed"
            },
            "line": 4,
            "name": "Создается файл для метрик",
            "match": {
              "location": "StepsDefinitions.fileForReportCreate()"
            },
            "keyword": "Given "
          },
          {
            "result": {
              "duration": 40552277333,
              "status": "passed"
            },
            "line": 5,
            "name": "Заказчик входит в систему со снятием метрик",
            "match": {
              "location": "StepsDefinitions.customerEntersSystemWithReport()"
            },
            "keyword": "When "
          },
          {
            "result": {
              "duration": 35814502810281,
              "error_message": "Element not found {By.id: header__authorization_loguot}\nExpected: visible\nScreenshot: file:/C:/Users/User3/IdeaProjects/Pr44/build/reports/tests/1512456924126.0.png\nTimeout: 90 s.\nCaused by: NoSuchElementException: no such element: Unable to locate element: {\"method\":\"id\",\"selector\":\"header__authorization_loguot\"}\r\n\tat com.codeborne.selenide.impl.WebElementSource.createElementNotFoundError(WebElementSource.java:31)\r\n\tat com.codeborne.selenide.impl.ElementFinder.createElementNotFoundError(ElementFinder.java:82)\r\n\tat com.codeborne.selenide.impl.WebElementSource.checkCondition(WebElementSource.java:59)\r\n\tat com.codeborne.selenide.commands.Should.should(Should.java:35)\r\n\tat com.codeborne.selenide.commands.Should.execute(Should.java:29)\r\n\tat com.codeborne.selenide.commands.Should.execute(Should.java:12)\r\n\tat com.codeborne.selenide.commands.Commands.execute(Commands.java:143)\r\n\tat com.codeborne.selenide.impl.SelenideElementProxy.dispatchAndRetry(SelenideElementProxy.java:87)\r\n\tat com.codeborne.selenide.impl.SelenideElementProxy.invoke(SelenideElementProxy.java:63)\r\n\tat com.sun.proxy.$Proxy16.should(Unknown Source)\r\n\tat CustomerPages.CustomerAuctionCreatingPage.nextStepPassing(CustomerAuctionCreatingPage.java:93)\r\n\tat CustomerPages.CustomerAuctionCreatingPage.createNewEA(CustomerAuctionCreatingPage.java:211)\r\n\tat steps.StepsDefinitions.customerCreatesAuction(StepsDefinitions.java:153)\r\n\tat ✽.And Заказчик создает три аукциона(performance.feature:7)\r\nCaused by: org.openqa.selenium.NoSuchElementException: no such element: Unable to locate element: {\"method\":\"id\",\"selector\":\"header__authorization_loguot\"}\n  (Session info: chrome\u003d62.0.3202.75)\n  (Driver info: chromedriver\u003d2.32.498550 (9dec58e66c31bcc53a9ce3c7226f0c1c5810906a),platform\u003dWindows NT 6.3.9600 x86_64) (WARNING: The server did not provide any stacktrace information)\nCommand duration or timeout: 5.02 seconds\nFor documentation on this error, please visit: http://seleniumhq.org/exceptions/no_such_element.html\nBuild info: version: \u00273.4.0\u0027, revision: \u0027unknown\u0027, time: \u0027unknown\u0027\nSystem info: host: \u0027USER\u0027, ip: \u0027172.19.14.199\u0027, os.name: \u0027Windows 8.1\u0027, os.arch: \u0027amd64\u0027, os.version: \u00276.3\u0027, java.version: \u00271.8.0_144\u0027\nDriver info: org.openqa.selenium.chrome.ChromeDriver\nCapabilities [{applicationCacheEnabled\u003dfalse, rotatable\u003dfalse, mobileEmulationEnabled\u003dfalse, networkConnectionEnabled\u003dfalse, chrome\u003d{chromedriverVersion\u003d2.32.498550 (9dec58e66c31bcc53a9ce3c7226f0c1c5810906a), userDataDir\u003dC:\\Users\\User3\\AppData\\Local\\Temp\\scoped_dir13268_24152}, takesHeapSnapshot\u003dtrue, pageLoadStrategy\u003dnormal, databaseEnabled\u003dfalse, handlesAlerts\u003dtrue, hasTouchScreen\u003dfalse, version\u003d62.0.3202.75, platform\u003dWIN8_1, browserConnectionEnabled\u003dfalse, nativeEvents\u003dtrue, acceptSslCerts\u003dtrue, locationContextEnabled\u003dtrue, webStorageEnabled\u003dtrue, browserName\u003dchrome, takesScreenshot\u003dtrue, javascriptEnabled\u003dtrue, cssSelectorsEnabled\u003dtrue, setWindowRect\u003dtrue, unexpectedAlertBehaviour\u003d}]\nSession ID: 784cc21dcb9d731c920a608605a33d7f\n*** Element info: {Using\u003did, value\u003dheader__authorization_loguot}\r\n\tat sun.reflect.GeneratedConstructorAccessor13.newInstance(Unknown Source)\r\n\tat sun.reflect.DelegatingConstructorAccessorImpl.newInstance(DelegatingConstructorAccessorImpl.java:45)\r\n\tat java.lang.reflect.Constructor.newInstance(Constructor.java:423)\r\n\tat org.openqa.selenium.remote.ErrorHandler.createThrowable(ErrorHandler.java:215)\r\n\tat org.openqa.selenium.remote.ErrorHandler.throwIfResponseFailed(ErrorHandler.java:167)\r\n\tat org.openqa.selenium.remote.RemoteWebDriver.execute(RemoteWebDriver.java:671)\r\n\tat org.openqa.selenium.remote.RemoteWebDriver.findElement(RemoteWebDriver.java:410)\r\n\tat org.openqa.selenium.remote.RemoteWebDriver.findElementById(RemoteWebDriver.java:453)\r\n\tat org.openqa.selenium.By$ById.findElement(By.java:218)\r\n\tat org.openqa.selenium.remote.RemoteWebDriver.findElement(RemoteWebDriver.java:402)\r\n\tat com.codeborne.selenide.impl.WebElementSelector.findElement(WebElementSelector.java:28)\r\n\tat com.codeborne.selenide.impl.ElementFinder.getWebElement(ElementFinder.java:56)\r\n\tat com.codeborne.selenide.impl.WebElementSource.checkCondition(WebElementSource.java:44)\r\n\tat com.codeborne.selenide.commands.Should.should(Should.java:35)\r\n\tat com.codeborne.selenide.commands.Should.execute(Should.java:29)\r\n\tat com.codeborne.selenide.commands.Should.execute(Should.java:12)\r\n\tat com.codeborne.selenide.commands.Commands.execute(Commands.java:143)\r\n\tat com.codeborne.selenide.impl.SelenideElementProxy.dispatchAndRetry(SelenideElementProxy.java:87)\r\n\tat com.codeborne.selenide.impl.SelenideElementProxy.invoke(SelenideElementProxy.java:63)\r\n\tat com.sun.proxy.$Proxy16.should(Unknown Source)\r\n\tat CustomerPages.CustomerAuctionCreatingPage.nextStepPassing(CustomerAuctionCreatingPage.java:93)\r\n\tat CustomerPages.CustomerAuctionCreatingPage.createNewEA(CustomerAuctionCreatingPage.java:211)\r\n\tat steps.StepsDefinitions.customerCreatesAuction(StepsDefinitions.java:153)\r\n\tat sun.reflect.NativeMethodAccessorImpl.invoke0(Native Method)\r\n\tat sun.reflect.NativeMethodAccessorImpl.invoke(NativeMethodAccessorImpl.java:62)\r\n\tat sun.reflect.DelegatingMethodAccessorImpl.invoke(DelegatingMethodAccessorImpl.java:43)\r\n\tat java.lang.reflect.Method.invoke(Method.java:498)\r\n\tat cucumber.runtime.Utils$1.call(Utils.java:37)\r\n\tat cucumber.runtime.Timeout.timeout(Timeout.java:13)\r\n\tat cucumber.runtime.Utils.invoke(Utils.java:31)\r\n\tat cucumber.runtime.java.JavaStepDefinition.execute(JavaStepDefinition.java:38)\r\n\tat cucumber.runtime.StepDefinitionMatch.runStep(StepDefinitionMatch.java:37)\r\n\tat cucumber.runtime.Runtime.runStep(Runtime.java:299)\r\n\tat cucumber.runtime.model.StepContainer.runStep(StepContainer.java:44)\r\n\tat cucumber.runtime.model.StepContainer.runSteps(StepContainer.java:39)\r\n\tat cucumber.runtime.model.CucumberScenario.run(CucumberScenario.java:44)\r\n\tat cucumber.runtime.junit.ExecutionUnitRunner.run(ExecutionUnitRunner.java:91)\r\n\tat cucumber.runtime.junit.FeatureRunner.runChild(FeatureRunner.java:63)\r\n\tat cucumber.runtime.junit.FeatureRunner.runChild(FeatureRunner.java:18)\r\n\tat org.junit.runners.ParentRunner$3.run(ParentRunner.java:290)\r\n\tat org.junit.runners.ParentRunner$1.schedule(ParentRunner.java:71)\r\n\tat org.junit.runners.ParentRunner.runChildren(ParentRunner.java:288)\r\n\tat org.junit.runners.ParentRunner.access$000(ParentRunner.java:58)\r\n\tat org.junit.runners.ParentRunner$2.evaluate(ParentRunner.java:268)\r\n\tat org.junit.runners.ParentRunner.run(ParentRunner.java:363)\r\n\tat cucumber.runtime.junit.FeatureRunner.run(FeatureRunner.java:70)\r\n\tat cucumber.api.junit.Cucumber.runChild(Cucumber.java:93)\r\n\tat cucumber.api.junit.Cucumber.runChild(Cucumber.java:37)\r\n\tat org.junit.runners.ParentRunner$3.run(ParentRunner.java:290)\r\n\tat org.junit.runners.ParentRunner$1.schedule(ParentRunner.java:71)\r\n\tat org.junit.runners.ParentRunner.runChildren(ParentRunner.java:288)\r\n\tat org.junit.runners.ParentRunner.access$000(ParentRunner.java:58)\r\n\tat org.junit.runners.ParentRunner$2.evaluate(ParentRunner.java:268)\r\n\tat org.junit.runners.ParentRunner.run(ParentRunner.java:363)\r\n\tat cucumber.api.junit.Cucumber.run(Cucumber.java:98)\r\n\tat org.junit.runner.JUnitCore.run(JUnitCore.java:137)\r\n\tat com.intellij.junit4.JUnit4IdeaTestRunner.startRunnerWithArgs(JUnit4IdeaTestRunner.java:68)\r\n\tat com.intellij.rt.execution.junit.IdeaTestRunner$Repeater.startRunnerWithArgs(IdeaTestRunner.java:47)\r\n\tat com.intellij.rt.execution.junit.JUnitStarter.prepareStreamsAndStart(JUnitStarter.java:242)\r\n\tat com.intellij.rt.execution.junit.JUnitStarter.main(JUnitStarter.java:70)\r\n",
              "status": "failed"
            },
            "comments": [
              {
                "line": 6,
                "value": "#And Заказчик снимает метрики"
              }
            ],
            "line": 7,
            "name": "Заказчик создает три аукциона",
            "match": {
              "location": "StepsDefinitions.customerCreatesAuction()"
            },
            "keyword": "And "
          },
          {
            "result": {
              "status": "skipped"
            },
            "line": 8,
            "name": "Заказчик получает информацию о созданных аукционах",
            "match": {
              "location": "StepsDefinitions.customerGetsInfoAboutAuctions()"
            },
            "keyword": "And "
          },
          {
            "result": {
              "status": "skipped"
            },
            "line": 9,
            "name": "Заказчик выходит из системы",
            "match": {
              "location": "StepsDefinitions.customerExitSystem()"
            },
            "keyword": "Then "
          },
          {
            "result": {
              "status": "skipped"
            },
            "line": 11,
            "name": "Поставщик \"1\" входит в систему со снятием метрик",
            "match": {
              "arguments": [
                {
                  "val": "1",
                  "offset": 11
                }
              ],
              "location": "StepsDefinitions.supplierEntersSystemWithReport(String)"
            },
            "keyword": "When "
          },
          {
            "result": {
              "status": "skipped"
            },
            "line": 12,
            "name": "Поставщик снимает метрики о заявках",
            "match": {
              "location": "StepsDefinitions.supplierCollectsMetricsAboutApplications()"
            },
            "keyword": "And "
          },
          {
            "result": {
              "status": "skipped"
            },
            "line": 13,
            "name": "Поставщик подает заявку на участие в торгах со снятием метрик",
            "match": {
              "location": "StepsDefinitions.supplierCreatesApplicationWithReport()"
            },
            "keyword": "Then "
          },
          {
            "result": {
              "status": "skipped"
            },
            "line": 14,
            "name": "Поставщик подает заявку на участие в торгах",
            "match": {
              "location": "StepsDefinitions.supplierCreatesApplication()"
            },
            "keyword": "Then "
          },
          {
            "result": {
              "status": "skipped"
            },
            "line": 15,
            "name": "Поставщик подает запрос на разъяснение документации",
            "match": {
              "location": "StepsDefinitions.supplierCreatesDocumentExplainingRequest()"
            },
            "keyword": "And "
          },
          {
            "result": {
              "status": "skipped"
            },
            "line": 16,
            "name": "Поставщик снимает метрики о торгах и контрактах",
            "match": {
              "location": "StepsDefinitions.supplierCollectsMetricsAboutContracts()"
            },
            "keyword": "And "
          },
          {
            "result": {
              "status": "skipped"
            },
            "line": 17,
            "name": "Поставщик выходит из системы",
            "match": {
              "location": "StepsDefinitions.supplierExitSystem()"
            },
            "keyword": "And "
          },
          {
            "result": {
              "status": "skipped"
            },
            "line": 19,
            "name": "Поставщик \"2\" входит в систему",
            "match": {
              "arguments": [
                {
                  "val": "2",
                  "offset": 11
                }
              ],
              "location": "StepsDefinitions.supplierEntersSystem(String)"
            },
            "keyword": "When "
          },
          {
            "result": {
              "status": "skipped"
            },
            "line": 20,
            "name": "Поставщик подает заявку на участие в торгах",
            "match": {
              "location": "StepsDefinitions.supplierCreatesApplication()"
            },
            "keyword": "Then "
          },
          {
            "result": {
              "status": "skipped"
            },
            "line": 21,
            "name": "Поставщик выходит из системы",
            "match": {
              "location": "StepsDefinitions.supplierExitSystem()"
            },
            "keyword": "And "
          },
          {
            "result": {
              "status": "skipped"
            },
            "line": 23,
            "name": "Администратор входит в систему",
            "match": {
              "location": "StepsDefinitions.adminEntersSystem()"
            },
            "keyword": "When "
          },
          {
            "result": {
              "status": "skipped"
            },
            "line": 24,
            "name": "Администратор открывает страницу ускорения процедур",
            "match": {
              "location": "StepsDefinitions.adminOpensAccelerationPage()"
            },
            "keyword": "And "
          },
          {
            "result": {
              "status": "skipped"
            },
            "line": 25,
            "name": "Администратор ускоряет закупки до этапа рассмотрения заявок",
            "match": {
              "location": "StepsDefinitions.adminAcceleratesTradeToApplicationsReception()"
            },
            "keyword": "Then "
          },
          {
            "result": {
              "status": "skipped"
            },
            "line": 26,
            "name": "Администратор выходит из системы",
            "match": {
              "location": "StepsDefinitions.adminExitSystem()"
            },
            "keyword": "And "
          },
          {
            "result": {
              "status": "skipped"
            },
            "line": 28,
            "name": "Заказчик входит в систему",
            "match": {
              "location": "StepsDefinitions.customerEntersSystem()"
            },
            "keyword": "When "
          },
          {
            "result": {
              "status": "skipped"
            },
            "line": 29,
            "name": "Заказчик открывает форму протокола рассмотрения заявок со снятием метрик",
            "match": {
              "location": "StepsDefinitions.customerOpensConsiderationFormWithReport()"
            },
            "keyword": "And "
          },
          {
            "result": {
              "status": "skipped"
            },
            "line": 30,
            "name": "Заказчик создает протокол рассмотрения двух заявок",
            "match": {
              "location": "StepsDefinitions.customerCreatesProtocolWithTwoApplications()"
            },
            "keyword": "Then "
          },
          {
            "result": {
              "status": "skipped"
            },
            "comments": [
              {
                "line": 31,
                "value": "#  And Заказчик открывает форму протокола рассмотрения заявок по закупке с номером"
              }
            ],
            "line": 32,
            "name": "Заказчик создает протокол рассмотрения одной заявки",
            "match": {
              "location": "StepsDefinitions.customerCreatesProtocolWithOneApplication()"
            },
            "keyword": "Then "
          },
          {
            "result": {
              "status": "skipped"
            },
            "comments": [
              {
                "line": 33,
                "value": "#  And Заказчик открывает форму протокола рассмотрения заявок по закупке с номером"
              }
            ],
            "line": 34,
            "name": "Заказчик создает протокол о признании закупки несостоявшейся",
            "match": {
              "location": "StepsDefinitions.customerCreatesProtocolWithoutApplications()"
            },
            "keyword": "Then "
          },
          {
            "result": {
              "status": "skipped"
            },
            "line": 35,
            "name": "Заказчик выходит из системы",
            "match": {
              "location": "StepsDefinitions.customerExitSystem()"
            },
            "keyword": "And "
          },
          {
            "result": {
              "status": "skipped"
            },
            "line": 37,
            "name": "Администратор входит в систему",
            "match": {
              "location": "StepsDefinitions.adminEntersSystem()"
            },
            "keyword": "When "
          },
          {
            "result": {
              "status": "skipped"
            },
            "line": 38,
            "name": "Администратор открывает страницу ускорения процедур",
            "match": {
              "location": "StepsDefinitions.adminOpensAccelerationPage()"
            },
            "keyword": "And "
          },
          {
            "result": {
              "status": "skipped"
            },
            "line": 39,
            "name": "Администратор ускоряет закупку до этапа начала торгов",
            "match": {
              "location": "StepsDefinitions.adminAcceleratesTradeToConsiderationEnds()"
            },
            "keyword": "Then "
          },
          {
            "result": {
              "status": "skipped"
            },
            "line": 40,
            "name": "Администратор выходит из системы",
            "match": {
              "location": "StepsDefinitions.adminExitSystem()"
            },
            "keyword": "And "
          },
          {
            "result": {
              "status": "skipped"
            },
            "line": 42,
            "name": "Поставщик \"1\" входит в систему",
            "match": {
              "arguments": [
                {
                  "val": "1",
                  "offset": 11
                }
              ],
              "location": "StepsDefinitions.supplierEntersSystem(String)"
            },
            "keyword": "When "
          },
          {
            "result": {
              "status": "skipped"
            },
            "line": 43,
            "name": "Поставщик открывает страницу подачи ценовых предложений",
            "match": {
              "location": "StepsDefinitions.supplierOpensBidSubmitPage()"
            },
            "keyword": "And "
          },
          {
            "result": {
              "status": "skipped"
            },
            "line": 44,
            "name": "Поставщик подает ценовое предложение на аукционе со снятием метрик",
            "match": {
              "location": "StepsDefinitions.supplierSubmitBitWithReport()"
            },
            "keyword": "Then "
          },
          {
            "result": {
              "status": "skipped"
            },
            "line": 45,
            "name": "Поставщик выходит из системы",
            "match": {
              "location": "StepsDefinitions.supplierExitSystem()"
            },
            "keyword": "And "
          },
          {
            "result": {
              "status": "skipped"
            },
            "line": 47,
            "name": "Поставщик \"2\" входит в систему",
            "match": {
              "arguments": [
                {
                  "val": "2",
                  "offset": 11
                }
              ],
              "location": "StepsDefinitions.supplierEntersSystem(String)"
            },
            "keyword": "When "
          },
          {
            "result": {
              "status": "skipped"
            },
            "line": 48,
            "name": "Поставщик открывает страницу подачи ценовых предложений",
            "match": {
              "location": "StepsDefinitions.supplierOpensBidSubmitPage()"
            },
            "keyword": "And "
          },
          {
            "result": {
              "status": "skipped"
            },
            "line": 49,
            "name": "Поставщик подает ценовое предложение на аукционе",
            "match": {
              "location": "StepsDefinitions.supplierSubmitBid()"
            },
            "keyword": "Then "
          },
          {
            "result": {
              "status": "skipped"
            },
            "line": 50,
            "name": "Поставщик выходит из системы",
            "match": {
              "location": "StepsDefinitions.supplierExitSystem()"
            },
            "keyword": "And "
          },
          {
            "result": {
              "status": "skipped"
            },
            "line": 52,
            "name": "Администратор входит в систему",
            "match": {
              "location": "StepsDefinitions.adminEntersSystem()"
            },
            "keyword": "When "
          },
          {
            "result": {
              "status": "skipped"
            },
            "line": 53,
            "name": "Администратор открывает страницу ускорения процедур",
            "match": {
              "location": "StepsDefinitions.adminOpensAccelerationPage()"
            },
            "keyword": "And "
          },
          {
            "result": {
              "status": "skipped"
            },
            "line": 54,
            "name": "Администратор ускоряет закупку до этапа подведения итогов торгов",
            "match": {
              "location": "StepsDefinitions.adminAcceleratesTradeToAuctionEnd()"
            },
            "keyword": "Then "
          },
          {
            "result": {
              "status": "skipped"
            },
            "line": 55,
            "name": "Администратор выходит из системы",
            "match": {
              "location": "StepsDefinitions.adminExitSystem()"
            },
            "keyword": "And "
          },
          {
            "result": {
              "status": "skipped"
            },
            "line": 57,
            "name": "Заказчик входит в систему",
            "match": {
              "location": "StepsDefinitions.customerEntersSystem()"
            },
            "keyword": "When "
          },
          {
            "result": {
              "status": "skipped"
            },
            "line": 58,
            "name": "Заказчик открывает форму протокола подведения итогов торгов",
            "match": {
              "location": "StepsDefinitions.customerOpensSummarizingForm()"
            },
            "keyword": "And "
          },
          {
            "result": {
              "status": "skipped"
            },
            "line": 59,
            "name": "Заказчик создает протокол подведения итогов торгов",
            "match": {
              "location": "StepsDefinitions.customerCreatesSummarizingProtoc()"
            },
            "keyword": "Then "
          },
          {
            "result": {
              "status": "skipped"
            },
            "line": 60,
            "name": "Заказчик отправляет контракт на подпись поставщику",
            "match": {
              "location": "StepsDefinitions.customersSendsContract()"
            },
            "keyword": "And "
          },
          {
            "result": {
              "status": "skipped"
            },
            "line": 61,
            "name": "Заказчик выходит из системы",
            "match": {
              "location": "StepsDefinitions.customerExitSystem()"
            },
            "keyword": "And "
          },
          {
            "result": {
              "status": "undefined"
            },
            "line": 63,
            "name": "Поставщик 1 входит в систему",
            "match": {},
            "keyword": "When "
          },
          {
            "result": {
              "status": "skipped"
            },
            "line": 64,
            "name": "Поставщик открывает контракт через треугольник \u0027Подпишите контракт\u0027 со снятием метрик",
            "match": {
              "location": "StepsDefinitions.supplierOpensContractPageViaTrgSignWithReport()"
            },
            "keyword": "And "
          },
          {
            "result": {
              "status": "skipped"
            },
            "line": 65,
            "name": "Поставщик создает протокол разногласий",
            "match": {
              "location": "StepsDefinitions.supplierCreatesDifferencesProtocol()"
            },
            "keyword": "Then "
          },
          {
            "result": {
              "status": "skipped"
            },
            "line": 66,
            "name": "Поставщик выходит из системы",
            "match": {
              "location": "StepsDefinitions.supplierExitSystem()"
            },
            "keyword": "And "
          },
          {
            "result": {
              "status": "skipped"
            },
            "line": 68,
            "name": "Заказчик входит в систему",
            "match": {
              "location": "StepsDefinitions.customerEntersSystem()"
            },
            "keyword": "When "
          },
          {
            "result": {
              "status": "skipped"
            },
            "line": 69,
            "name": "Заказчик открывает контракт через треугольник \u0027Переотправьте контракт\u0027",
            "match": {
              "location": "StepsDefinitions.customerOpensContractPageViaTrgResend()"
            },
            "keyword": "And "
          },
          {
            "result": {
              "status": "skipped"
            },
            "line": 70,
            "name": "Заказчик вносит изменения в контракт",
            "match": {
              "location": "StepsDefinitions.customerMakesChangesToContract()"
            },
            "keyword": "Then "
          },
          {
            "result": {
              "status": "skipped"
            },
            "line": 71,
            "name": "Заказчик выходит из системы",
            "match": {
              "location": "StepsDefinitions.customerExitSystem()"
            },
            "keyword": "And "
          },
          {
            "result": {
              "status": "skipped"
            },
            "line": 73,
            "name": "Поставщик \"1\" входит в систему",
            "match": {
              "arguments": [
                {
                  "val": "1",
                  "offset": 11
                }
              ],
              "location": "StepsDefinitions.supplierEntersSystem(String)"
            },
            "keyword": "When "
          },
          {
            "result": {
              "status": "skipped"
            },
            "line": 74,
            "name": "Поставщик открывает контракт через треугольник \u0027Подпишите контракт\u0027",
            "match": {
              "location": "StepsDefinitions.supplierOpensContractPageViaTrgSign()"
            },
            "keyword": "And "
          },
          {
            "result": {
              "status": "skipped"
            },
            "line": 75,
            "name": "Поставщик подписывает контракт",
            "match": {
              "location": "StepsDefinitions.supplierSignsContract()"
            },
            "keyword": "Then "
          },
          {
            "result": {
              "status": "skipped"
            },
            "line": 76,
            "name": "Поставщик выходит из системы",
            "match": {
              "location": "StepsDefinitions.supplierExitSystem()"
            },
            "keyword": "And "
          },
          {
            "result": {
              "status": "skipped"
            },
            "line": 78,
            "name": "Администратор входит в систему",
            "match": {
              "location": "StepsDefinitions.adminEntersSystem()"
            },
            "keyword": "When "
          },
          {
            "result": {
              "status": "skipped"
            },
            "line": 79,
            "name": "Администратор открывает страницу сроков подписания контракта",
            "match": {
              "location": "StepsDefinitions.adminOpensContractAccelerationPage()"
            },
            "keyword": "And "
          },
          {
            "result": {
              "status": "skipped"
            },
            "line": 80,
            "name": "Администратор сдвигает регламентный срок подписания контракта",
            "match": {
              "location": "StepsDefinitions.adminAcceleratesContractConclusion()"
            },
            "keyword": "Then "
          },
          {
            "result": {
              "status": "skipped"
            },
            "line": 81,
            "name": "Администратор выходит из системы",
            "match": {
              "location": "StepsDefinitions.adminExitSystem()"
            },
            "keyword": "And "
          },
          {
            "result": {
              "status": "skipped"
            },
            "line": 83,
            "name": "Заказчик входит в систему",
            "match": {
              "location": "StepsDefinitions.customerEntersSystem()"
            },
            "keyword": "When "
          },
          {
            "result": {
              "status": "skipped"
            },
            "line": 84,
            "name": "Заказчик открывает контракт через треугольник \u0027Подпишите контракт\u0027",
            "match": {
              "location": "StepsDefinitions.customerOpensContractPageViaTrgSing()"
            },
            "keyword": "And "
          },
          {
            "result": {
              "status": "skipped"
            },
            "line": 85,
            "name": "Заказчик подписывает контракт",
            "match": {
              "location": "StepsDefinitions.customerSignsContract()"
            },
            "keyword": "Then "
          },
          {
            "result": {
              "status": "skipped"
            },
            "line": 86,
            "name": "Заказчик выходит из системы",
            "match": {
              "location": "StepsDefinitions.customerExitSystem()"
            },
            "keyword": "And "
          },
          {
            "result": {
              "status": "skipped"
            },
            "line": 87,
            "name": "Закрытие файла отчета",
            "match": {
              "location": "StepsDefinitions.reportFileClose()"
            },
            "keyword": "Then "
          }
        ]
      }
    ],
    "name": "performance test 1, collecting metric to excel file",
    "description": "",
    "id": "performance-test-1,-collecting-metric-to-excel-file",
    "keyword": "Feature",
    "uri": "performance.feature"
  }
]